flask_humanify/__init__.py
flask_humanify/download_ipset.py
flask_humanify/humanify.py
flask_humanify/memory_server.py
flask_humanify/utils.py
flask_humanify-0.2.9.dist-info/licenses/LICENSE
flask_humanify-0.2.9.dist-info/METADATA
flask_humanify-0.2.9.dist-info/WHEEL
flask_humanify-0.2.9.dist-info/top_level.txt
flask_humanify-0.2.9.dist-info/RECORD
