Metadata-Version: 2.4
Name: flask-Humanify
Version: 0.2.9
Summary: Protect against bots and DDoS attacks
Author-email: TN3W <tn3w@protonmail.com>
License-Expression: Apache-2.0
Project-URL: Homepage, https://github.com/tn3w/flask-Humanify
Project-URL: Documentation, https://github.com/tn3w/flask-Humanify
Project-URL: Repository, https://github.com/tn3w/flask-Humanify.git
Project-URL: Issues, https://github.com/tn3w/flask-Humanify/issues
Classifier: Development Status :: 4 - Beta
Classifier: Environment :: Web Environment
Classifier: Framework :: Flask
Classifier: Intended Audience :: Developers
Classifier: Operating System :: OS Independent
Classifier: Programming Language :: Python
Classifier: Programming Language :: Python :: 3
Classifier: Programming Language :: Python :: 3.9
Classifier: Programming Language :: Python :: 3.10
Classifier: Programming Language :: Python :: 3.11
Classifier: Programming Language :: Python :: 3.12
Classifier: Programming Language :: Python :: 3.13
Classifier: Topic :: Internet :: WWW/HTTP :: Dynamic Content
Classifier: Topic :: Software Development :: Libraries :: Python Modules
Requires-Python: >=3.6
License-File: LICENSE
Requires-Dist: Flask
Requires-Dist: netaddr
Requires-Dist: opencv-python-headless
Requires-Dist: numpy
Requires-Dist: cryptography
Requires-Dist: scipy
Requires-Dist: pydub
Requires-Dist: crawler-user-agents
Requires-Dist: audioop-lts>=0.2.1; python_version >= "3.13"
Dynamic: license-file
